dataminer/__init__.py
dataminer/datax/__init__.py
dataminer/datax/job_helpers.py
dataminer/datax/runner.py
dataminer/sqla/__init__.py
dataminer/sqla/engine_helpers.py
dataminer/sqla/inspect_helpers.py
dataminer/sqla/query_helpers.py
dataminer-0.1.5.dist-info/LICENSE
dataminer-0.1.5.dist-info/METADATA
dataminer-0.1.5.dist-info/WHEEL
dataminer-0.1.5.dist-info/top_level.txt
dataminer-0.1.5.dist-info/RECORD
